{"nodes": [{"id": "internal_cli_validate_go", "label": "validate.go", "file_type": "code", "source_file": "internal/cli/validate.go", "source_location": "L1"}, {"id": "validate_newvalidatecommand", "label": "newValidateCommand()", "file_type": "code", "source_file": "internal/cli/validate.go", "source_location": "L9"}, {"id": "validate_enabledword", "label": "enabledWord()", "file_type": "code", "source_file": "internal/cli/validate.go", "source_location": "L33"}], "edges": [{"source": "internal_cli_validate_go", "target": "fmt", "relation": "imports_from", "confidence": "EXTRACTED", "source_file": "internal/cli/validate.go", "source_location": "L4", "weight": 1.0}, {"source": "internal_cli_validate_go", "target": "cobra", "relation": "imports_from", "confidence": "EXTRACTED", "source_file": "internal/cli/validate.go", "source_location": "L6", "weight": 1.0}, {"source": "internal_cli_validate_go", "target": "validate_newvalidatecommand", "relation": "contains", "confidence": "EXTRACTED", "source_file": "internal/cli/validate.go", "source_location": "L9", "weight": 1.0}, {"source": "internal_cli_validate_go", "target": "validate_enabledword", "relation": "contains", "confidence": "EXTRACTED", "source_file": "internal/cli/validate.go", "source_location": "L33", "weight": 1.0}, {"source": "validate_newvalidatecommand", "target": "validate_enabledword", "relation": "calls", "confidence": "EXTRACTED", "source_file": "internal/cli/validate.go", "source_location": "L27", "weight": 1.0}], "raw_calls": [{"caller_nid": "validate_newvalidatecommand", "callee": "loadGraph", "source_file": "internal/cli/validate.go", "source_location": "L21"}, {"caller_nid": "validate_newvalidatecommand", "callee": "Fprintf", "source_file": "internal/cli/validate.go", "source_location": "L25"}, {"caller_nid": "validate_newvalidatecommand", "callee": "OutOrStdout", "source_file": "internal/cli/validate.go", "source_location": "L25"}, {"caller_nid": "validate_newvalidatecommand", "callee": "len", "source_file": "internal/cli/validate.go", "source_location": "L27"}, {"caller_nid": "validate_newvalidatecommand", "callee": "len", "source_file": "internal/cli/validate.go", "source_location": "L27"}]}